{
  "chapters": {
    "1": {
      "pendingViews": 1,
      "lastIncrement": "2025-12-04T16:06:49.673Z",
      "lastUpdate": "2025-12-04T00:15:40+07:00"
    },
    "2.1": {
      "pendingViews": 2,
      "lastIncrement": "2025-12-04T16:17:40.084Z",
      "lastUpdate": "2025-12-04T00:15:40+07:00"
    },
    "2.2": {
      "pendingViews": 2,
      "lastIncrement": "2025-12-04T16:18:56.233Z",
      "lastUpdate": "2025-12-04T00:15:40+07:00"
    },
    "2.3": {
      "pendingViews": 2,
      "lastIncrement": "2025-12-04T13:49:00.885Z",
      "lastUpdate": "2025-12-04T00:15:40+07:00"
    },
    "3.1": {
      "pendingViews": 3,
      "lastIncrement": "2025-12-04T15:33:11.075Z",
      "lastUpdate": "2025-12-04T00:15:40+07:00"
    }
  },
  "lastUpdated": "2025-12-04T00:15:40+07:00"
}